r.v
`timescale 1ns/1ps

module r (
    input  wire        clk,

    // -------------------------
    // Port A
    // -------------------------
    input  wire        we_a,
    input  wire [7:0]  addr_a,
    input  wire [22:0] din_a,
    output reg  [22:0] dout_a,

    // -------------------------
    // Port B
    // -------------------------
    input  wire        we_b,
    input  wire [7:0]  addr_b,
    input  wire [22:0] din_b,
    output reg  [22:0] dout_b
);

    // 256 locations × 23 bits
    reg [22:0] mem [0:255];

    always @(posedge clk) begin

        // =========================
        // PORT A
        // =========================

        if (we_a)
            mem[addr_a] <= din_a;

        dout_a <= mem[addr_a];


        // =========================
        // PORT B
        // =========================

        if (we_b)
            mem[addr_b] <= din_b;

        dout_b <= mem[addr_b];

    end

endmodule

tb_r.v
`timescale 1ns/1ps

module tb_r;

    reg        clk;

    // Port A
    reg        we_a;
    reg [7:0]  addr_a;
    reg [22:0] din_a;
    wire [22:0] dout_a;

    // Port B
    reg        we_b;
    reg [7:0]  addr_b;
    reg [22:0] din_b;
    wire [22:0] dout_b;


    // ==========================================
    // DUT
    // ==========================================

   r uut (
        .clk    (clk),

        .we_a   (we_a),
        .addr_a (addr_a),
        .din_a  (din_a),
        .dout_a (dout_a),

        .we_b   (we_b),
        .addr_b (addr_b),
        .din_b  (din_b),
        .dout_b (dout_b)
    );


    // ==========================================
    // CLOCK
    // ==========================================

    initial begin
        clk = 0;
        forever #5 clk = ~clk;
    end


    // ==========================================
    // VCD DUMP
    // ==========================================

    initial begin
        $dumpfile("r.vcd");
        $dumpvars(0, tb_r);
    end


    // ==========================================
    // TEST
    // ==========================================

    initial begin

        // Initial values
        we_a   = 0;
        addr_a = 0;
        din_a  = 0;

        we_b   = 0;
        addr_b = 0;
        din_b  = 0;


        // ======================================
        // TEST 1
        // Port A writes 100 to address 10
        // ======================================

        #10;

        we_a   = 1;
        addr_a = 8'd10;
        din_a  = 23'd100;

        #10;

        we_a = 0;


        // ======================================
        // TEST 2
        // Port B writes 200 to address 20
        // ======================================

        addr_b = 8'd20;
        din_b  = 23'd200;
        we_b   = 1;

        #10;

        we_b = 0;


        // ======================================
        // TEST 3
        // Read two different addresses
        // simultaneously
        //
        // Port A → address 10 → 100
        // Port B → address 20 → 200
        // ======================================

        addr_a = 8'd10;
        addr_b = 8'd20;

        #10;

        $display("--------------------------------");
        $display("TEST 3");
        $display("Port A: Address = %d, Data = %d",
                 addr_a, dout_a);
        $display("Port B: Address = %d, Data = %d",
                 addr_b, dout_b);
        $display("--------------------------------");


        // ======================================
        // TEST 4
        // Read different addresses
        //
        // Port A → address 20
        // Port B → address 10
        // ======================================

        addr_a = 8'd20;
        addr_b = 8'd10;

        #10;

        $display("--------------------------------");
        $display("TEST 4");
        $display("Port A: Address = %d, Data = %d",
                 addr_a, dout_a);
        $display("Port B: Address = %d, Data = %d",
                 addr_b, dout_b);
        $display("--------------------------------");


        // ======================================
        // TEST 5
        // Both ports read SAME address
        // ======================================

        addr_a = 8'd10;
        addr_b = 8'd10;

        #10;

        $display("--------------------------------");
        $display("TEST 5 - SAME ADDRESS");
        $display("Port A: Address = %d, Data = %d",
                 addr_a, dout_a);
        $display("Port B: Address = %d, Data = %d",
                 addr_b, dout_b);
        $display("--------------------------------");


        // ======================================
        // TEST 6
        // Simultaneous WRITE
        //
        // Port A → RAM[30] = 300
        // Port B → RAM[40] = 400
        // ======================================

        we_a   = 1;
        addr_a = 8'd30;
        din_a  = 23'd300;

        we_b   = 1;
        addr_b = 8'd40;
        din_b  = 23'd400;

        #10;

        we_a = 0;
        we_b = 0;


        // ======================================
        // Read RAM[30] and RAM[40]
        // simultaneously
        // ======================================

        addr_a = 8'd30;
        addr_b = 8'd40;

        #10;

        $display("--------------------------------");
        $display("TEST 6 - SIMULTANEOUS WRITE/READ");
        $display("Port A: Address = %d, Data = %d",
                 addr_a, dout_a);
        $display("Port B: Address = %d, Data = %d",
                 addr_b, dout_b);
        $display("--------------------------------");


        // ======================================
        // END
        // ======================================

        #10;

        $finish;

    end

endmodule

inital test/r.vcd
$date
	Fri Sep  4 14:33:34 2026
$end
$version
	Icarus Verilog
$end
$timescale
	1ps
$end
$scope module tb_r $end
$var wire 23 ! dout_b [22:0] $end
$var wire 23 " dout_a [22:0] $end
$var reg 8 # addr_a [7:0] $end
$var reg 8 $ addr_b [7:0] $end
$var reg 1 % clk $end
$var reg 23 & din_a [22:0] $end
$var reg 23 ' din_b [22:0] $end
$var reg 1 ( we_a $end
$var reg 1 ) we_b $end
$scope module uut $end
$var wire 8 * addr_a [7:0] $end
$var wire 8 + addr_b [7:0] $end
$var wire 1 % clk $end
$var wire 23 , din_a [22:0] $end
$var wire 23 - din_b [22:0] $end
$var wire 1 ( we_a $end
$var wire 1 ) we_b $end
$var reg 23 . dout_a [22:0] $end
$var reg 23 / dout_b [22:0] $end
$upscope $end
$upscope $end
$enddefinitions $end
$comment Show the parameter values. $end
$dumpall
$end
#0
$dumpvars
bx /
bx .
b0 -
b0 ,
b0 +
b0 *
0)
0(
b0 '
b0 &
0%
b0 $
b0 #
bx "
bx !
$end
#5000
1%
#10000
0%
b1100100 &
b1100100 ,
b1010 #
b1010 *
1(
#15000
1%
#20000
0%
1)
b11001000 '
b11001000 -
b10100 $
b10100 +
0(
#25000
b1100100 "
b1100100 .
1%
#30000
0%
0)
#35000
b11001000 !
b11001000 /
1%
#40000
0%
b1010 $
b1010 +
b10100 #
b10100 *
#45000
b1100100 !
b1100100 /
b11001000 "
b11001000 .
1%
#50000
0%
b1010 #
b1010 *
#55000
b1100100 "
b1100100 .
1%
#60000
0%
b110010000 '
b110010000 -
b101000 $
b101000 +
1)
b100101100 &
b100101100 ,
b11110 #
b11110 *
1(
#65000
bx !
bx /
bx "
bx .
1%
#70000
0%
0)
0(
#75000
b110010000 !
b110010000 /
b100101100 "
b100101100 .
1%
