ram.v
module ram (
    input  wire        clk,

    input  wire [7:0]  addr_a,
    input  wire [22:0] din_a,
    input  wire        we_a,
    output reg  [22:0] dout_a,

    input  wire [7:0]  addr_b,
    input  wire [22:0] din_b,
    input  wire        we_b,
    output reg  [22:0] dout_b,

    input  wire [7:0]  rd_addr,
    output wire [22:0] rd_data
);
    reg [22:0] mem [0:255];

    always @(posedge clk) begin
        if (we_a) mem[addr_a] <= din_a;
        dout_a <= mem[addr_a];
    end

    always @(posedge clk) begin
        if (we_b) mem[addr_b] <= din_b;
        dout_b <= mem[addr_b];
    end

    assign rd_data = mem[rd_addr];
endmodule

inital test/ram_tb.v
`timescale 1ns/1ps
//------------------------------------------------------------------
// Testbench for: ram (true dual-port RAM, 256 x 23-bit,
//                 registered ports A/B + combinational read port)
//
// Run:
//   iverilog -o sim.out ram.v ram_tb.v
//   vvp sim.out
//   (optional) gtkwave ram_tb.vcd
//------------------------------------------------------------------
module ram_tb;

    reg         clk;
    reg  [7:0]  addr_a, addr_b, rd_addr;
    reg  [22:0] din_a,  din_b;
    reg         we_a,   we_b;
    wire [22:0] dout_a, dout_b, rd_data;

    integer checks = 0;
    integer errors = 0;

    ram dut (
        .clk     (clk),
        .addr_a  (addr_a), .din_a (din_a), .we_a (we_a), .dout_a (dout_a),
        .addr_b  (addr_b), .din_b (din_b), .we_b (we_b), .dout_b (dout_b),
        .rd_addr (rd_addr), .rd_data (rd_data)
    );

    // 100 MHz clock
    always #5 clk = ~clk;

    // self-checking task
    task check23(input [22:0] got, input [22:0] exp, input [8*48-1:0] name);
        begin
            checks = checks + 1;
            if (got !== exp) begin
                errors = errors + 1;
                $display("[FAIL] %0t ns  %0s : expected=%h got=%h", $time, name, exp, got);
            end else begin
                $display("[PASS] %0t ns  %0s : got=%h", $time, name, got);
            end
        end
    endtask

    initial begin
        $dumpfile("ram_tb.vcd");
        $dumpvars(0, ram_tb);

        clk    = 0;
        we_a   = 0; we_b   = 0;
        addr_a = 0; addr_b = 0; rd_addr = 0;
        din_a  = 0; din_b  = 0;

        //--------------------------------------------------------
        // T1: Port A write, then Port A read-back
        //--------------------------------------------------------
        @(negedge clk);
        addr_a = 8'd10; din_a = 23'h1AAAAA; we_a = 1;
        @(negedge clk);
        we_a = 0; addr_a = 8'd10;
        @(negedge clk);
        check23(dout_a, 23'h1AAAAA, "T1 PortA write-then-read");

        //--------------------------------------------------------
        // T2: Port B write, then Port B read-back
        //--------------------------------------------------------
        @(negedge clk);
        addr_b = 8'd20; din_b = 23'h2BBBBB; we_b = 1;
        @(negedge clk);
        we_b = 0; addr_b = 8'd20;
        @(negedge clk);
        check23(dout_b, 23'h2BBBBB, "T2 PortB write-then-read");

        //--------------------------------------------------------
        // T3: Async rd_data reflects memory content (no clk needed)
        //--------------------------------------------------------
        rd_addr = 8'd10; #1;
        check23(rd_data, 23'h1AAAAA, "T3 AsyncRead sees PortA data");

        rd_addr = 8'd20; #1;
        check23(rd_data, 23'h2BBBBB, "T3 AsyncRead sees PortB data");

        //--------------------------------------------------------
        // T4: Cross-port visibility - A writes, B reads same addr
        //--------------------------------------------------------
        @(negedge clk);
        addr_a = 8'd30; din_a = 23'h3CCCCC; we_a = 1;
        @(negedge clk);
        we_a = 0; addr_b = 8'd30;
        @(negedge clk);
        check23(dout_b, 23'h3CCCCC, "T4 PortB reads PortA write");

        //--------------------------------------------------------
        // T5: read-old-data-on-write hazard (same port, same addr,
        //     write and read requested in the same clock)
        //--------------------------------------------------------
        @(negedge clk);
        addr_a = 8'd40; din_a = 23'h044444; we_a = 1;   // preload
        @(negedge clk);
        we_a = 0;
        @(negedge clk);
        addr_a = 8'd40; din_a = 23'h055555; we_a = 1;   // write new + read same addr
        @(negedge clk);
        we_a = 0;
        check23(dout_a, 23'h044444, "T5 PortA reads OLD data while writing NEW");
        @(negedge clk);
        addr_a = 8'd40;
        @(negedge clk);
        check23(dout_a, 23'h055555, "T5 PortA sees NEW data next cycle");

        //--------------------------------------------------------
        // T6: address boundaries 0 and 255
        //--------------------------------------------------------
        @(negedge clk);
        addr_a = 8'd0;   din_a = 23'h000001; we_a = 1;
        addr_b = 8'd255; din_b = 23'h7FFFFF; we_b = 1;
        @(negedge clk);
        we_a = 0; we_b = 0;
        addr_a = 8'd0; addr_b = 8'd255;
        @(negedge clk);
        check23(dout_a, 23'h000001, "T6 Boundary addr 0   (PortA)");
        check23(dout_b, 23'h7FFFFF, "T6 Boundary addr 255 (PortB)");

        //--------------------------------------------------------
        // T7: simultaneous same-address write from both ports.
        // Not a pass/fail check - the RTL has no arbitration for
        // this case, so the winner is simulator/tool dependent.
        // Reported for awareness only.
        //--------------------------------------------------------
        @(negedge clk);
        addr_a = 8'd50; din_a = 23'h0A0A0A; we_a = 1;
        addr_b = 8'd50; din_b = 23'h0B0B0B; we_b = 1;
        @(negedge clk);
        we_a = 0; we_b = 0;
        rd_addr = 8'd50; #1;
        $display("[INFO] %0t ns  T7 simultaneous A/B write to addr 50 -> mem=%h (undefined arbitration, flag for RTL review)", $time, rd_data);

        //--------------------------------------------------------
        @(negedge clk);
        $display("----------------------------------------------------");
        $display("TOTAL CHECKS = %0d   ERRORS = %0d", checks, errors);
        if (errors == 0)
            $display("RESULT: ALL TESTS PASSED");
        else
            $display("RESULT: %0d TEST(S) FAILED", errors);
        $display("----------------------------------------------------");

        $finish;
    end

endmodule

inital test/ram_tb.vcd
$date
	Fri Sep  4 09:36:50 2026
$end
$version
	Icarus Verilog
$end
$timescale
	1ps
$end
$scope module ram_tb $end
$var wire 23 ! rd_data [22:0] $end
$var wire 23 " dout_b [22:0] $end
$var wire 23 # dout_a [22:0] $end
$var reg 8 $ addr_a [7:0] $end
$var reg 8 % addr_b [7:0] $end
$var reg 1 & clk $end
$var reg 23 ' din_a [22:0] $end
$var reg 23 ( din_b [22:0] $end
$var reg 8 ) rd_addr [7:0] $end
$var reg 1 * we_a $end
$var reg 1 + we_b $end
$var integer 32 , checks [31:0] $end
$var integer 32 - errors [31:0] $end
$scope module dut $end
$var wire 8 . addr_a [7:0] $end
$var wire 8 / addr_b [7:0] $end
$var wire 1 & clk $end
$var wire 23 0 din_a [22:0] $end
$var wire 23 1 din_b [22:0] $end
$var wire 8 2 rd_addr [7:0] $end
$var wire 23 3 rd_data [22:0] $end
$var wire 1 * we_a $end
$var wire 1 + we_b $end
$var reg 23 4 dout_a [22:0] $end
$var reg 23 5 dout_b [22:0] $end
$upscope $end
$scope task check23 $end
$var reg 23 6 exp [22:0] $end
$var reg 23 7 got [22:0] $end
$var reg 384 8 name [383:0] $end
$upscope $end
$upscope $end
$enddefinitions $end
$comment Show the parameter values. $end
$dumpall
$end
#0
$dumpvars
bx 8
bx 7
bx 6
bx 5
bx 4
bx 3
b0 2
b0 1
b0 0
b0 /
b0 .
b0 -
b0 ,
0+
0*
b0 )
b0 (
b0 '
0&
b0 %
b0 $
bx #
bx "
bx !
$end
#5000
1&
#10000
1*
b110101010101010101010 '
b110101010101010101010 0
b1010 $
b1010 .
0&
#15000
1&
#20000
0*
0&
#25000
b110101010101010101010 #
b110101010101010101010 4
1&
#30000
b1 ,
b10101000011000100100000010100000110111101110010011101000100000100100000011101110111001001101001011101000110010100101101011101000110100001100101011011100010110101110010011001010110000101100100 8
b110101010101010101010 6
b110101010101010101010 7
0&
#35000
1&
#40000
1+
b1010111011101110111011 (
b1010111011101110111011 1
b10100 %
b10100 /
0&
#45000
1&
#50000
0+
0&
#55000
b1010111011101110111011 "
b1010111011101110111011 5
1&
#60000
b110101010101010101010 !
b110101010101010101010 3
b1010 )
b1010 2
b10 ,
b10101000011001000100000010100000110111101110010011101000100001000100000011101110111001001101001011101000110010100101101011101000110100001100101011011100010110101110010011001010110000101100100 8
b1010111011101110111011 6
b1010111011101110111011 7
0&
#61000
b1010111011101110111011 !
b1010111011101110111011 3
b10100 )
b10100 2
b11 ,
b1010100001100110010000001000001011100110111100101101110011000110101001001100101011000010110010000100000011100110110010101100101011100110010000001010000011011110111001001110100010000010010000001100100011000010111010001100001 8
b110101010101010101010 6
b110101010101010101010 7
#62000
b100 ,
b1010100001100110010000001000001011100110111100101101110011000110101001001100101011000010110010000100000011100110110010101100101011100110010000001010000011011110111001001110100010000100010000001100100011000010111010001100001 8
b1010111011101110111011 6
b1010111011101110111011 7
#65000
1&
#70000
1*
b1111001100110011001100 '
b1111001100110011001100 0
b11110 $
b11110 .
0&
#75000
bx #
bx 4
1&
#80000
b11110 %
b11110 /
0*
0&
#85000
b1111001100110011001100 #
b1111001100110011001100 4
b1111001100110011001100 "
b1111001100110011001100 5
1&
#90000
b101 ,
b101010000110100001000000101000001101111011100100111010001000010001000000111001001100101011000010110010001110011001000000101000001101111011100100111010001000001001000000111011101110010011010010111010001100101 8
b1111001100110011001100 6
b1111001100110011001100 7
0&
#95000
1&
#100000
1*
b1000100010001000100 '
b1000100010001000100 0
b101000 $
b101000 .
0&
#105000
bx #
bx 4
1&
#110000
0*
0&
#115000
b1000100010001000100 #
b1000100010001000100 4
1&
#120000
1*
b1010101010101010101 '
b1010101010101010101 0
0&
#125000
1&
#130000
b110 ,
b101010000110101001000000101000001101111011100100111010001000001001000000111001001100101011000010110010001110011001000000100111101001100010001000010000001100100011000010111010001100001001000000111011101101000011010010110110001100101001000000111011101110010011010010111010001101001011011100110011100100000010011100100010101010111 8
b1000100010001000100 6
b1000100010001000100 7
0*
0&
#135000
b1010101010101010101 #
b1010101010101010101 4
1&
#140000
0&
#145000
1&
#150000
b111 ,
b10101000011010100100000010100000110111101110010011101000100000100100000011100110110010101100101011100110010000001001110010001010101011100100000011001000110000101110100011000010010000001101110011001010111100001110100001000000110001101111001011000110110110001100101 8
b1010101010101010101 6
b1010101010101010101 7
0&
#155000
1&
#160000
1+
b11111111111111111111111 (
b11111111111111111111111 1
b11111111 %
b11111111 /
1*
b1 '
b1 0
b0 $
b0 .
0&
#165000
bx #
bx 4
bx "
bx 5
1&
#170000
0+
0*
0&
#175000
b11111111111111111111111 "
b11111111111111111111111 5
b1 #
b1 4
1&
#180000
b1001 ,
b1010100001101100010000001000010011011110111010101101110011001000110000101110010011110010010000001100001011001000110010001110010001000000011001000110101001101010010000000101000010100000110111101110010011101000100001000101001 8
b11111111111111111111111 6
b11111111111111111111111 7
0&
#185000
1&
#190000
1+
b10110000101100001011 (
b10110000101100001011 1
b110010 %
b110010 /
1*
b10100000101000001010 '
b10100000101000001010 0
b110010 $
b110010 .
0&
#195000
bx "
bx 5
bx #
bx 4
1&
#200000
b10110000101100001011 !
b10110000101100001011 3
b110010 )
b110010 2
0+
0*
0&
#205000
b10110000101100001011 #
b10110000101100001011 4
b10110000101100001011 "
b10110000101100001011 5
1&
